{
  "migrations": [
    {
      "cli": "nx",
      "version": "16.8.0-beta.4",
      "description": "Update to Cypress v13. Most noteable change is video recording is off by default. This migration will only update if the workspace is already on Cypress v12. https://docs.cypress.io/guides/references/migration-guide#Migrating-to-Cypress-130",
      "implementation": "./src/migrations/update-16-8-0/cypress-13",
      "package": "@nrwl/cypress",
      "name": "update-16-8-0-cypress-13"
    },
    {
      "version": "16.8.0",
      "description": "update-16-8-0-add-ignored-files",
      "implementation": "./src/migrations/update-16-8-0-add-ignored-files/update-16-8-0-add-ignored-files",
      "package": "@nrwl/linter",
      "name": "update-16-8-0-add-ignored-files"
    }
  ]
}
